gitlabsolute/__init__.py
gitlabsolute/__main__.py
gitlabsolute/gitlab.py
gitlabsolute/lexer.py
gitlabsolute/pipeline/__init__.py
gitlabsolute/pipeline/delete.py
gitlabsolute/pipeline/list.py
gitlabsolute/project_badge/__init__.py
gitlabsolute/project_badge/duplicate.py
gitlabsolute/runner/__init__.py
gitlabsolute/runner/delete.py
gitlabsolute/runner/list.py
gitlabsolute-1.1.8.dist-info/LICENSE
gitlabsolute-1.1.8.dist-info/METADATA
gitlabsolute-1.1.8.dist-info/WHEEL
gitlabsolute-1.1.8.dist-info/entry_points.txt
gitlabsolute-1.1.8.dist-info/top_level.txt
gitlabsolute-1.1.8.dist-info/zip-safe
gitlabsolute-1.1.8.dist-info/RECORD
