Metadata-Version: 2.1
Name: gitlabsolute
Version: 1.1.8
Summary: Helper and convenience scripts to help with common GitLab actions.
Author-email: Julien Lecomte <julien@lecomte.at>
License: MIT
Project-URL: Homepage, https://gitlab.com/cappysan/gitlabsolute
Project-URL: Documentation, https://gitlabsolute.docs.cappysan.dev
Project-URL: Source code, https://gitlab.com/cappysan/gitlabsolute
Project-URL: Bug tracker, https://gitlab.com/cappysan/gitlabsolute/-/issues
Classifier: License :: OSI Approved :: MIT License
Classifier: Development Status :: 4 - Beta
Classifier: Programming Language :: Python :: 3 :: Only
Classifier: Programming Language :: Python :: 3.7
Classifier: Programming Language :: Python :: 3.8
Classifier: Programming Language :: Python :: 3.9
Classifier: Programming Language :: Python :: 3.10
Classifier: Programming Language :: Python :: 3.11
Classifier: Programming Language :: Python :: 3.12
Requires-Python: >=3.7
License-File: LICENSE
Requires-Dist: imxdparser
Requires-Dist: ply<4.0.0
Requires-Dist: python-gitlab
Requires-Dist: pyyaml
Requires-Dist: torxtools>=1.1.6
Provides-Extra: dev
